<?xml version="1.0" encoding="UTF-8"?>
<beans xmlns="http://www.springframework.org/schema/beans"
       xmlns:p="http://www.springframework.org/schema/p"
       xmlns:jdbc="http://www.springframework.org/schema/jdbc"
       xmlns:xsi="http://www.w3.org/2001/XMLSchema-instance"
       xsi:schemaLocation="http://www.springframework.org/schema/beans
        http://www.springframework.org/schema/beans/spring-beans-2.5.xsd
        http://www.springframework.org/schema/jdbc 
        http://www.springframework.org/schema/jdbc/spring-jdbc-4.2.xsd">

    <bean id="jobOperator"
          class="org.springframework.batch.core.launch.support.SimpleJobOperator"
          p:jobLauncher-ref="jobLauncher" p:jobExplorer-ref="jobExplorer"
          p:jobRepository-ref="jobRepository" p:jobRegistry-ref="jobRegistry"/>

    <bean id="jobExplorer"
          class="org.springframework.batch.core.explore.support.JobExplorerFactoryBean"
          p:dataSource-ref="dataSource"/>

    <bean id="jobRegistry"
          class="org.springframework.batch.core.configuration.support.MapJobRegistry"/>

    <bean class="org.springframework.batch.core.configuration.support.JobRegistryBeanPostProcessor">
        <property name="jobRegistry" ref="jobRegistry"/>
    </bean>

    <bean id="jobLauncher"
          class="org.springframework.batch.core.launch.support.SimpleJobLauncher">
        <property name="jobRepository" ref="jobRepository"/>
    </bean>

    <bean id="jobRepository"
          class="org.springframework.batch.core.repository.support.JobRepositoryFactoryBean"
          p:dataSource-ref="dataSource" p:transactionManager-ref="transactionManager"/>

    <bean id="dataSource" class="com.zaxxer.hikari.HikariDataSource">
        <property name="dataSourceClassName" value="${db.datasource.class.name}"/>
        <property name="dataSourceProperties">
            <props>
                <prop key="user">${jobRepository.datasource.username}</prop>
                <prop key="password">${jobRepository.datasource.password}</prop>
                <prop key="databaseName">${jobRepository.datasource.databaseName}</prop>
                <prop key="portNumber">${jobRepository.datasource.portNumber}</prop>
                <prop key="serverName">${jobRepository.datasource.serverName}</prop>
            </props>
        </property>
        <property name="maximumPoolSize" value="${maxConcurrencyLimit}"/>
    </bean>

    <bean id="transactionManager" class="org.springframework.jdbc.datasource.DataSourceTransactionManager"
          lazy-init="true">
        <property name="dataSource" ref="dataSource"/>
    </bean>

    <!-- create job-meta tables automatically -->
    <jdbc:initialize-database data-source="dataSource">
        <jdbc:script location="${jobRepository.datasource.drop-repository-tables}"/>
        <jdbc:script location="${jobRepository.datasource.data-repository-schema}"/>
    </jdbc:initialize-database>

    <bean id="placeholderProperties" class="org.springframework.beans.factory.config.PropertyPlaceholderConfigurer">
        <property name="location" value="classpath:application.properties"/>
        <property name="systemPropertiesModeName" value="SYSTEM_PROPERTIES_MODE_OVERRIDE"/>
        <property name="ignoreUnresolvablePlaceholders" value="true"/>
        <property name="order" value="1"/>
    </bean>
</beans>